tissuelab_sdk/__init__.py
tissuelab_sdk/wrapper/__init__.py
tissuelab_sdk/wrapper/common.py
tissuelab_sdk/wrapper/windows.py
tissuelab_sdk-0.1.13.dist-info/METADATA
tissuelab_sdk-0.1.13.dist-info/WHEEL
tissuelab_sdk-0.1.13.dist-info/top_level.txt
tissuelab_sdk-0.1.13.dist-info/RECORD
